README.txt
setup.cfg
setup.py
docs/HISTORY.txt
docs/LICENSE.GPL
docs/LICENSE.txt
docs/MANUAL.txt
raptus/__init__.py
raptus.article.fader.egg-info/PKG-INFO
raptus.article.fader.egg-info/SOURCES.txt
raptus.article.fader.egg-info/dependency_links.txt
raptus.article.fader.egg-info/entry_points.txt
raptus.article.fader.egg-info/namespace_packages.txt
raptus.article.fader.egg-info/not-zip-safe
raptus.article.fader.egg-info/requires.txt
raptus.article.fader.egg-info/top_level.txt
raptus/article/__init__.py
raptus/article/fader/__init__.py
raptus/article/fader/configure.zcml
raptus/article/fader/browser/__init__.py
raptus/article/fader/browser/configure.zcml
raptus/article/fader/browser/fader.init.js
raptus/article/fader/browser/fader.pt
raptus/article/fader/browser/fader.py
raptus/article/fader/browser/fader_full.gif
raptus/article/fader/browser/fader_left.gif
raptus/article/fader/browser/fader_right.gif
raptus/article/fader/browser/fader_teaser.gif
raptus/article/fader/i18n/raptus.article-de.po
raptus/article/fader/i18n/raptus.article-fr.po
raptus/article/fader/i18n/raptus.article.pot
raptus/article/fader/profiles/default/cssregistry.xml
raptus/article/fader/profiles/default/jsregistry.xml
raptus/article/fader/profiles/default/metadata.xml
raptus/article/fader/profiles/default/propertiestool.xml
raptus/article/fader/profiles/default/skins.xml
raptus/article/fader/profiles/default/viewlets.xml
raptus/article/fader/skins/raptus_article_fader/raptus.article.fader.css.dtml